blogengine/__init__.py
blogengine/blogengine.py
blogengine/run.py
blogengine/entity/__init__.py
blogengine/entity/page.py
blogengine/entity/post.py
blogengine/entity/site.py
blogengine/lib/__init__.py
blogengine/output/__init__.py
blogengine/output/websiteoutput.py
blogengine/source/__init__.py
blogengine/source/evernotesource.py
blogengine/upload/__init__.py
blogengine/upload/ftp.py
python_blogengine-1.1.9.dist-info/DESCRIPTION.rst
python_blogengine-1.1.9.dist-info/entry_points.txt
python_blogengine-1.1.9.dist-info/METADATA
python_blogengine-1.1.9.dist-info/metadata.json
python_blogengine-1.1.9.dist-info/RECORD
python_blogengine-1.1.9.dist-info/top_level.txt
python_blogengine-1.1.9.dist-info/WHEEL
