Metadata-Version: 2.0
Name: python-blogengine
Version: 1.1.9
Summary: Reads notes from your Evernote account and builds a beautiful blog out of it
Home-page: https://github.com/tspycher/python-blogengine
Author: Thomas Spycher
Author-email: me@tspycher.com
License: MIT
Keywords: evernote blog engine
Platform: UNKNOWN
Classifier: Development Status :: 5 - Production/Stable
Classifier: Intended Audience :: Developers
Classifier: License :: OSI Approved :: MIT License
Classifier: Programming Language :: Python :: 2
Classifier: Programming Language :: Python :: 2.6
Classifier: Programming Language :: Python :: 2.7
Requires-Dist: Jinja2
Requires-Dist: evernote
Requires-Dist: python-slugify
Requires-Dist: feedgen
